{
  "name": "Disney.com",
  "path": "dcom",
  "description": "<p>Created features and experiences across domestic &amp international Disney portfolio of sites</p><p>Agile software development within Sinatra/Backbone architecture</p><p>Refactored codebase to minimize code bloat and page load times, and increase general standards and legibility</p><p>Defined and created the CSS coding standards and style guide that was distributed to all devs</p><p>Transition wireframes into code for prototypes and production, incorporating interactivity, animated elements, and fluid responsive states</p><p><a href=\"https://www.webbyawards.com/winners/2015/websites/general-website/youth/disneycom/\" target=\"blank\">2015 Webby Award Honoree:Youth Website</a></p>",
  "color": "#2b92e7",
  "date": "2013-2018",
  "tools": [
    "HTML5",
    "Backbone",
    "jQuery",
    "Mustache",
    "Sinatra",
    "Sass",
    "IA/UX"
  ],
  "link": {
    "title": "view site",
    "href": "http://www.disney.com"
  },
  "banner": {
    "src": "dcom_cars.jpg",
    "alt": "Cars Homepage",
    "classes": "browser styled"
  },
  "sections": [
    {
      "images": [
        {
          "src": "gallery_mickey.jpg",
          "alt": "Mickey Gallery",
          "classes": "browser styled"
        },
        {
          "src": "gallery_mickey_zoom.jpg",
          "alt": "Mickey Gallery Zoomed Image",
          "classes": "browser styled"
        },
        {
          "video": {
            "src": "answer_reveal",
            "controls": true
          },
          "alt": "Answer Reveal Module",
          "classes": "browser styled image-right",
          "caption": "An answer/reveal module with configurable text, images, custom dynamic transitions for the \"reveal\" state (such as push, fade, and flip), and triggered to play on hover or click. Can be used for jokes and basic Q&ampA"
        },
        {
          "video": {
            "src": "interactive_grid",
            "controls": true
          },
          "alt": "Interactive Grid Module",
          "classes": "browser styled",
          "caption": "An interactive flexible grid with configurable sprite animations that are triggered on hover or on page load, optional links, and designed to responsively resize to distribute objects in multiple rows. If there are an odd number of objects, the grid compensates fill 100% of the row width"
        },
        {
          "src": "princess_disney.jpg",
          "alt": "Ariel Homepage",
          "classes": "browser styled set-aspect"
        }
      ]
    }
  ]
}
